feynlab_cloud/__init__.py
feynlab_cloud/service.py
feynLab_cloud-1.0.5.dist-info/LICENSE
feynLab_cloud-1.0.5.dist-info/METADATA
feynLab_cloud-1.0.5.dist-info/WHEEL
feynLab_cloud-1.0.5.dist-info/top_level.txt
feynLab_cloud-1.0.5.dist-info/RECORD
